gphoto_2_album/__init__.py
gphoto_2_album-0.0.1.dist-info/METADATA
gphoto_2_album-0.0.1.dist-info/WHEEL
gphoto_2_album-0.0.1.dist-info/top_level.txt
gphoto_2_album-0.0.1.dist-info/RECORD
