Metadata-Version: 2.1
Name: gphoto-2-album
Version: 0.0.1
Summary: Return photo list from google photo link.
Home-page: https://github.com/gaoyunzhi/gphoto_2_album
Author: Yunzhi Gao
Author-email: gaoyunzhi@gmail.com
License: UNKNOWN
Platform: UNKNOWN
Classifier: Programming Language :: Python :: 3
Classifier: License :: OSI Approved :: GNU General Public License v3 (GPLv3)
Classifier: Operating System :: OS Independent
Requires-Python: >=3.0
Requires-Dist: cached-url
Requires-Dist: bs4
Requires-Dist: telegram-util
